{
    "os": "macOS-13.2.1-arm64-arm-64bit",
    "python": "3.10.9",
    "heartbeatAt": "2023-03-01T11:27:42.998284",
    "startedAt": "2023-03-01T11:27:42.331957",
    "docker": null,
    "cuda": null,
    "args": [],
    "state": "running",
    "program": "/Users/bartlomiejsobieski/Osobisty/VSC/deep_learning_project_1/models/example_convnet.py",
    "codePath": "models/example_convnet.py",
    "git": {
        "remote": "https://github.com/sobieskibj/deep-learning_project-1.git",
        "commit": "0e430c85867c141e9eadc7940ac0917e82e360df"
    },
    "email": "sobieski.bartlomiej.jan@gmail.com",
    "root": "/Users/bartlomiejsobieski/Osobisty/VSC/deep_learning_project_1",
    "host": "MacBook-Pro-Bartomiej.local",
    "username": "bartlomiejsobieski",
    "executable": "/Users/bartlomiejsobieski/Osobisty/miniconda3/envs/deep_learning_msc/bin/python",
    "cpu_count": 8,
    "cpu_count_logical": 8,
    "disk": {
        "total": 228.27386474609375,
        "used": 8.327995300292969
    },
    "gpuapple": {
        "type": "arm",
        "vendor": "Apple"
    },
    "memory": {
        "total": 16.0
    }
}
